cleanmydata/__init__.py
cleanmydata/contextualSpellCheck.py
cleanmydata/functions.py
cleanmydata/language_detection.py
cleanmydata-1.0.6.dist-info/METADATA
cleanmydata-1.0.6.dist-info/WHEEL
cleanmydata-1.0.6.dist-info/top_level.txt
cleanmydata-1.0.6.dist-info/RECORD
