Metadata-Version: 2.1
Name: cleanmydata
Version: 1.0.6
Summary: Library for data cleaning operations
Author: Pranav Bapat
Author-email: pranav.g33k@gmail.com
License: MIT
Project-URL: Bug Tracker, https://github.com/pranavnbapat/cleanmydata
Keywords: data,cleaning,data cleaning
Requires-Dist: pandas
Requires-Dist: numpy
Requires-Dist: spacy
Requires-Dist: contextualSpellCheck
Requires-Dist: fasttext-langdetect
